pwa/__init__.py
pwa/admin.py
pwa/apps.py
pwa/models.py
pwa/tests.py
pwa/urls.py
pwa/views.py
pwa/migrations/__init__.py
pwa/static/manifest.json
pwa/static/style.css
pwa/static/icons/aurss.192x192.png
pwa/static/icons/aurss.512x512.png
pwa/static/icons/aurss.96x96.png
pwa/templates/404.html
pwa/templates/base.html
pwa/templates/sw.js
pwa/templates/pwa/fill_dynamic_cache.html
pwa/templates/pwa/must_not_cache.html
pwa/templates/pwa/my_page.html
pwa/templates/pwa/offline.html
pwa/templates/pwa/random_response.html
pwa/templates/pwa/say_something.html
django_smart_pwa-1.1.1.dist-info/LICENSE
django_smart_pwa-1.1.1.dist-info/METADATA
django_smart_pwa-1.1.1.dist-info/WHEEL
django_smart_pwa-1.1.1.dist-info/top_level.txt
django_smart_pwa-1.1.1.dist-info/RECORD
